flask_google_cloud_logger/__init__.py
flask_google_cloud_logger/formatter.py
flask_google_cloud_logger/hooks.py
test/__init__.py
test/conftest.py
test/test_flask_google_cloud_formatter.py
test/test_hooks.py
flask_google_cloud_logger-0.2.1.dist-info/METADATA
flask_google_cloud_logger-0.2.1.dist-info/WHEEL
flask_google_cloud_logger-0.2.1.dist-info/top_level.txt
flask_google_cloud_logger-0.2.1.dist-info/RECORD
